springboot_generator/__init__.py
springboot_generator/main.py
springboot_generator-0.3.0.dist-info/licenses/LICENSE
springboot_generator-0.3.0.dist-info/METADATA
springboot_generator-0.3.0.dist-info/WHEEL
springboot_generator-0.3.0.dist-info/entry_points.txt
springboot_generator-0.3.0.dist-info/top_level.txt
springboot_generator-0.3.0.dist-info/RECORD
