Metadata-Version: 2.4
Name: springboot-generator
Version: 0.3.0
Summary: Interactive Spring Boot project generator (Java 17/21, Docker, Swagger, modular)
Home-page: https://github.com/YOUR_GITHUB/springboot-generator
Author: YOUR_NAME
Author-email: your@email.com
License: Apache-2.0
Classifier: Programming Language :: Python :: 3
Classifier: License :: OSI Approved :: Apache Software License
Classifier: Operating System :: OS Independent
Classifier: Environment :: Console
Classifier: Topic :: Software Development :: Code Generators
Requires-Python: >=3.9
License-File: LICENSE
Dynamic: license-file
